SellPandas/__init__.py
SellPandas/plots.py
SellPandas/preprocessing.py
SellPandas/utils.py
SellPandas-0.0.2.dist-info/LICENSE
SellPandas-0.0.2.dist-info/METADATA
SellPandas-0.0.2.dist-info/WHEEL
SellPandas-0.0.2.dist-info/top_level.txt
SellPandas-0.0.2.dist-info/RECORD
